spyl/__init__.py
spyl-1.0.1.dist-info/LICENSE
spyl-1.0.1.dist-info/METADATA
spyl-1.0.1.dist-info/WHEEL
spyl-1.0.1.dist-info/top_level.txt
spyl-1.0.1.dist-info/RECORD
