Metadata-Version: 2.1
Name: spyl
Version: 1.0.1
Summary: A simple python logger
Author-email: PentaMine <author@example.com>
Project-URL: Homepage, https://github.com/PentaMine/python-logger
Project-URL: Bug Tracker, https://github.com/PentaMine/python-logger/issues
Classifier: Programming Language :: Python :: 3
Classifier: License :: OSI Approved :: MIT License
Classifier: Operating System :: OS Independent
Requires-Python: >=3.7
License-File: LICENSE
Requires-Dist: colorama (>=0.4.5)
